ovos_lang_detector_classics_plugin/__init__.py
ovos_lang_detector_classics_plugin/cld3.py
ovos_lang_detector_classics_plugin/neon_cld2.py
ovos_lang_detector_classics_plugin/neon_fastlang.py
ovos_lang_detector_classics_plugin/neon_langdetect.py
ovos_lang_detector_classics_plugin-0.0.1a1.dist-info/METADATA
ovos_lang_detector_classics_plugin-0.0.1a1.dist-info/WHEEL
ovos_lang_detector_classics_plugin-0.0.1a1.dist-info/entry_points.txt
ovos_lang_detector_classics_plugin-0.0.1a1.dist-info/top_level.txt
ovos_lang_detector_classics_plugin-0.0.1a1.dist-info/RECORD
